Workbook

Sheet About
A1: Do central bank wins translate to household wins? Data workbook
A2: Ben Coppage. Companion data for the brief at https://bcoppage-ic.github.io/Portfolio/brief.html
A4: Tab | B4: Contents | C4: Frequency and range | D4: Source | E4: Notes
A5: Inflation | B5: U.S. CPI and Euro Area HICP inflation, year-over-year %, with a 2% target line | C5: Monthly, Jan 2015 to Aug 2025 | D5: U.S.: BLS CPI via FRED. Euro Area: Eurostat HICP. | E5: U.S. peak in this series is 9.0% (June 2022). BLS reports the headline peak as 9.1%.
A6: GDP_Growth | B6: Real GDP growth, year-over-year % | C6: Quarterly, 2015 Q1 to 2025 Q2 | D6: U.S.: BEA via FRED. Euro Area: Eurostat. | E6: Holds the GDP chart (2023 Q1 to 2025 Q2).
A7: Saving_Rate | B7: Household saving rate, % of disposable income | C7: Quarterly, 2015 Q1 to 2025 Q2 | D7: U.S.: BEA personal saving rate via FRED. Euro Area: Eurostat household saving rate. | E7: The U.S. rate is net and the Euro Area rate is gross, so levels are not strictly comparable.
A8: Household_Debt | B8: Household debt, % of GDP | C8: Quarterly, 2015 Q1 to 2025 Q1 | D8: Bank for International Settlements (BIS).
A9: Policy_Rates | B9: Effective federal funds rate and ECB main refinancing rate, % (not lagged) | C9: Monthly, Jan 2014 to Aug 2024 | D9: FRED series FEDFUNDS and ECBMRRFR. | E9: Ends Aug 2024. Does not include the rate cuts that followed.
A10: Unemployment | B10: Unemployment rate, % | C10: Monthly, Jan 2015 to Aug 2025 | D10: U.S.: BLS via FRED. Euro Area: Eurostat. | E10: Holds the unemployment chart and the Phillips curve (2023 to 2025).
A11: Rates_Inflation_Lagged | B11: Policy rates lagged 12 months next to inflation. Data for Exhibit 1. | C11: Monthly, Jan 2015 to Aug 2025 | D11: Built from Policy_Rates and Inflation. | E11: Each rate cell is a formula that pulls the Policy_Rates value from 12 months earlier. Example: Jan 2015 shows the Jan 2014 rate.
A12: Household_Panel | B12: Saving rates and debt-to-GDP side by side. Data for Exhibit 3. | C12: Quarterly, 2015 Q1 to 2025 Q2 | D12: Built from Saving_Rate and Household_Debt. | E12: Debt for 2025 Q2 was not yet published.
A14: Why a 12-month lag
A15: Rate changes act on prices with a delay (Friedman, 1961). A meta-analysis puts the average lag to the peak effect on prices at 29 months (Havranek and Rusnak, 2013). This workbook uses 12 months, a conservative choice at the short end of that range.
A17: References
A18: Friedman, M. (1961). The lag in effect of monetary policy. Journal of Political Economy, 69(5), 447-466.
A19: Havranek, T., and Rusnak, M. (2013). Transmission lags of monetary policy: A meta-analysis. International Journal of Central Banking, 9(4), 39-76.

Sheet Inflation
A1: observation_date | B1: U.S. Inflation (CPI, YoY %) | C1: Euro Area Inflation (HICP, YoY %) | D1: Target_2%
A2: 42005 | B2: -0.22993 | C2: -0.60704 | D2: 2
A3: 42036 | B3: -0.08703 | C3: -0.29252 | D3: 2
A4: 42064 | B4: -0.02203 | C4: -0.06995 | D4: 2
A5: 42095 | B5: -0.10403 | C5: 0.20954 | D5: 2
A6: 42125 | B6: 0.03503 | C6: 0.58929 | D6: 2
A7: 42156 | B7: 0.17957 | C7: 0.48888 | D7: 2
A8: 42186 | B8: 0.22569 | C8: 0.54228 | D8: 2
A9: 42217 | B9: 0.2413 | C9: 0.43134 | D9: 2
A10: 42248 | B10: 0.00884 | C10: 0.18975 | D10: 2
A11: 42278 | B11: 0.12762 | C11: 0.38977 | D11: 2
A12: 42309 | B12: 0.43632 | C12: 0.13016 | D12: 2
A13: 42339 | B13: 0.63872 | C13: 0.25055 | D13: 2
... A129: 45870 | B129: 2.93922 | C129: 2.04371 | D129: 2

Sheet GDP_Growth
A1: IND | B1: QUARTER | C1: U.S. Real GDP Growth (% YoY) | D1: Euro Area Real GDP Growth (% YoY)
A2: 0 | B2: 2015Q1 | C2: 3.9693 | D2: 1.86701
A3: =A2+1 -> 1 | B3: 2015Q2 | C3: 3.27909 | D3: 2.05289
A4: =A3+1 -> 2 | B4: 2015Q3 | C4: 2.44732 | D4: 1.98475
A5: =A4+1 -> 3 | B5: 2015Q4 | C5: 2.11986 | D5: 2.11679
A6: =A5+1 -> 4 | B6: 2016Q1 | C6: 1.79502 | D6: 1.82898
A7: =A6+1 -> 5 | B7: 2016Q2 | C7: 1.49325 | D7: 1.59783
A8: =A7+1 -> 6 | B8: 2016Q3 | C8: 1.80576 | D8: 1.66405
A9: =A8+1 -> 7 | B9: 2016Q4 | C9: 2.18157 | D9: 1.90781
A10: =A9+1 -> 8 | B10: 2017Q1 | C10: 2.08746 | D10: 2.26119
A11: =A10+1 -> 9 | B11: 2017Q2 | C11: 2.33041 | D11: 2.73762
A12: =A11+1 -> 10 | B12: 2017Q3 | C12: 2.41082 | D12: 2.99768
A13: =A12+1 -> 11 | B13: 2017Q4 | C13: 2.99414 | D13: 3.05678
A14: =A13+1 -> 12 | B14: 2018Q1 | C14: 3.32881 | D14: 2.27182
... A43: =A42+1 -> 41 | B43: 2025Q2 | C43: 2.08047 | D43: 1.48418

Sheet Saving_Rate
A1: =GDP_Growth!B1 -> QUARTER | B1: U.S. Household Saving Rate (%) | C1: Euro Area Household Saving Rate (%)
A2: =GDP_Growth!B2 -> 2015Q1 | B2: 6.2 | C2: 12.4
A3: =GDP_Growth!B3 -> 2015Q2 | B3: 5.8 | C3: 12.52
A4: =GDP_Growth!B4 -> 2015Q3 | B4: 5.7 | C4: 12.44
A5: =GDP_Growth!B5 -> 2015Q4 | B5: 5.7 | C5: 12.53
A6: =GDP_Growth!B6 -> 2016Q1 | B6: 5.9 | C6: 12.55
A7: =GDP_Growth!B7 -> 2016Q2 | B7: 5.2 | C7: 12.67
A8: =GDP_Growth!B8 -> 2016Q3 | B8: 5.1 | C8: 12.65
A9: =GDP_Growth!B9 -> 2016Q4 | B9: 5.2 | C9: 12.55
A10: =GDP_Growth!B10 -> 2017Q1 | B10: 5.5 | C10: 12.46
A11: =GDP_Growth!B11 -> 2017Q2 | B11: 6 | C11: 12.51
A12: =GDP_Growth!B12 -> 2017Q3 | B12: 6 | C12: 12.41
A13: =GDP_Growth!B13 -> 2017Q4 | B13: 5.5 | C13: 12.47
... A43: =GDP_Growth!B43 -> 2025Q2 | B43: 5.3 | C43: 15.2

Sheet Household_Debt
A1: =GDP_Growth!B1 -> QUARTER | B1: U.S. Household Debt‑to‑GDP | C1: Euro Area Household Debt‑to‑GDP
A2: =GDP_Growth!B2 -> 2015Q1 | B2: 77.577032 | C2: 59.5
A3: =GDP_Growth!B3 -> 2015Q2 | B3: 78.278557 | C3: 59.2
A4: =GDP_Growth!B4 -> 2015Q3 | B4: 78.94176 | C4: 58.8
A5: =GDP_Growth!B5 -> 2015Q4 | B5: 78.97695 | C5: 58.6
A6: =GDP_Growth!B6 -> 2016Q1 | B6: 76.935054 | C6: 58.1
A7: =GDP_Growth!B7 -> 2016Q2 | B7: 77.625582 | C7: 58.2
A8: =GDP_Growth!B8 -> 2016Q3 | B8: 78.517168 | C8: 58.1
A9: =GDP_Growth!B9 -> 2016Q4 | B9: 79.060261 | C9: 58
A10: =GDP_Growth!B10 -> 2017Q1 | B10: 76.095778 | C10: 58.1
A11: =GDP_Growth!B11 -> 2017Q2 | B11: 76.881874 | C11: 58
A12: =GDP_Growth!B12 -> 2017Q3 | B12: 77.637351 | C12: 57.7
A13: =GDP_Growth!B13 -> 2017Q4 | B13: 78.625094 | C13: 57.5
... A42: =GDP_Growth!B42 -> 2025Q1 | B42: 68.100243 | C42: 51.1
A43: =GDP_Growth!B43 -> 2025Q2

Sheet Policy_Rates
A1: observation_date | B1: Fed funds rate (%) [FEDFUNDS] | C1: ECB MRO rate (%) [ECBMRRFR]
A2: 41640 | B2: 0.07 | C2: 0.25
A3: 41671 | B3: 0.07 | C3: 0.25
A4: 41699 | B4: 0.08 | C4: 0.25
A5: 41730 | B5: 0.09 | C5: 0.25
A6: 41760 | B6: 0.09 | C6: 0.25
A7: 41791 | B7: 0.1 | C7: 0.15
A8: 41821 | B8: 0.09 | C8: 0.15
A9: 41852 | B9: 0.09 | C9: 0.15
A10: 41883 | B10: 0.09 | C10: 0.05
A11: 41913 | B11: 0.09 | C11: 0.05
A12: 41944 | B12: 0.09 | C12: 0.05
A13: 41974 | B13: 0.12 | C13: 0.05
... A129: 45505 | B129: 5.33 | C129: 4.25

Sheet Unemployment
A1: observation_date | B1: U.S. Unemployment Rate (%) | C1: Euro Area Unemployment Rate (%)
A2: 42005 | B2: 5.7 | C2: 11.38097
A3: 42036 | B3: 5.5 | C3: 11.32276
A4: 42064 | B4: 5.4 | C4: 11.32063
A5: 42095 | B5: 5.4 | C5: 11.19181
A6: 42125 | B6: 5.6 | C6: 11.15202
A7: 42156 | B7: 5.3 | C7: 11.08076
A8: 42186 | B8: 5.2 | C8: 10.84722
A9: 42217 | B9: 5.1 | C9: 10.76235
A10: 42248 | B10: 5 | C10: 10.7122
A11: 42278 | B11: 5 | C11: 10.72173
A12: 42309 | B12: 5.1 | C12: 10.60625
A13: 42339 | B13: 5 | C13: 10.57403
... A129: 45870 | B129: 4.3 | C129: 6.25288

Sheet Rates_Inflation_Lagged
A1: observation_date | B1: Fed funds rate (lagged 12 mo.) | C1: ECB MRO rate (lagged 12 mo.) | D1: CPI (YoY %) | E1: HICP (YoY %)
A2: 42005 | B2: =Policy_Rates!B2 -> 0.07 | C2: =Policy_Rates!C2 -> 0.25 | D2: -0.22993 | E2: -0.60704
A3: 42036 | B3: =Policy_Rates!B3 -> 0.07 | C3: =Policy_Rates!C3 -> 0.25 | D3: -0.08703 | E3: -0.29252
A4: 42064 | B4: =Policy_Rates!B4 -> 0.08 | C4: =Policy_Rates!C4 -> 0.25 | D4: -0.02203 | E4: -0.06995
A5: 42095 | B5: =Policy_Rates!B5 -> 0.09 | C5: =Policy_Rates!C5 -> 0.25 | D5: -0.10403 | E5: 0.20954
A6: 42125 | B6: =Policy_Rates!B6 -> 0.09 | C6: =Policy_Rates!C6 -> 0.25 | D6: 0.03503 | E6: 0.58929
A7: 42156 | B7: =Policy_Rates!B7 -> 0.1 | C7: =Policy_Rates!C7 -> 0.15 | D7: 0.17957 | E7: 0.48888
A8: 42186 | B8: =Policy_Rates!B8 -> 0.09 | C8: =Policy_Rates!C8 -> 0.15 | D8: 0.22569 | E8: 0.54228
A9: 42217 | B9: =Policy_Rates!B9 -> 0.09 | C9: =Policy_Rates!C9 -> 0.15 | D9: 0.2413 | E9: 0.43134
A10: 42248 | B10: =Policy_Rates!B10 -> 0.09 | C10: =Policy_Rates!C10 -> 0.05 | D10: 0.00884 | E10: 0.18975
A11: 42278 | B11: =Policy_Rates!B11 -> 0.09 | C11: =Policy_Rates!C11 -> 0.05 | D11: 0.12762 | E11: 0.38977
A12: 42309 | B12: =Policy_Rates!B12 -> 0.09 | C12: =Policy_Rates!C12 -> 0.05 | D12: 0.43632 | E12: 0.13016
A13: 42339 | B13: =Policy_Rates!B13 -> 0.12 | C13: =Policy_Rates!C13 -> 0.05 | D13: 0.63872 | E13: 0.25055
... A129: 45870 | B129: =Policy_Rates!B129 -> 5.33 | C129: =Policy_Rates!C129 -> 4.25 | D129: 2.93922 | E129: 2.04371

Sheet Household_Panel
A1: =GDP_Growth!B1 -> QUARTER | B1: U.S. Household Saving Rate (%) | C1: Euro Area Household Saving Rate (%) | D1: U.S. Household Debt‑to‑GDP | E1: Euro Area Household Debt‑to‑GDP
A2: =GDP_Growth!B2 -> 2015Q1 | B2: 6.2 | C2: 12.4 | D2: 77.577032 | E2: 59.5
A3: =GDP_Growth!B3 -> 2015Q2 | B3: 5.8 | C3: 12.52 | D3: 78.278557 | E3: 59.2
A4: =GDP_Growth!B4 -> 2015Q3 | B4: 5.7 | C4: 12.44 | D4: 78.94176 | E4: 58.8
A5: =GDP_Growth!B5 -> 2015Q4 | B5: 5.7 | C5: 12.53 | D5: 78.97695 | E5: 58.6
A6: =GDP_Growth!B6 -> 2016Q1 | B6: 5.9 | C6: 12.55 | D6: 76.935054 | E6: 58.1
A7: =GDP_Growth!B7 -> 2016Q2 | B7: 5.2 | C7: 12.67 | D7: 77.625582 | E7: 58.2
A8: =GDP_Growth!B8 -> 2016Q3 | B8: 5.1 | C8: 12.65 | D8: 78.517168 | E8: 58.1
A9: =GDP_Growth!B9 -> 2016Q4 | B9: 5.2 | C9: 12.55 | D9: 79.060261 | E9: 58
A10: =GDP_Growth!B10 -> 2017Q1 | B10: 5.5 | C10: 12.46 | D10: 76.095778 | E10: 58.1
A11: =GDP_Growth!B11 -> 2017Q2 | B11: 6 | C11: 12.51 | D11: 76.881874 | E11: 58
A12: =GDP_Growth!B12 -> 2017Q3 | B12: 6 | C12: 12.41 | D12: 77.637351 | E12: 57.7
A13: =GDP_Growth!B13 -> 2017Q4 | B13: 5.5 | C13: 12.47 | D13: 78.625094 | E13: 57.5
... A42: =GDP_Growth!B42 -> 2025Q1 | B42: 5.1 | C42: 15.19 | D42: 68.100243 | E42: 51.1
A43: =GDP_Growth!B43 -> 2025Q2 | B43: 5.3 | C43: 15.2
